MANIFEST.in
README.rst
setup.py
docs/HISTORY.txt
docs/LICENSE.txt
docs/OLD_HISTORY.txt
src/stxnext/__init__.py
src/stxnext.staticdeployment.egg-info/PKG-INFO
src/stxnext.staticdeployment.egg-info/SOURCES.txt
src/stxnext.staticdeployment.egg-info/dependency_links.txt
src/stxnext.staticdeployment.egg-info/entry_points.txt
src/stxnext.staticdeployment.egg-info/namespace_packages.txt
src/stxnext.staticdeployment.egg-info/not-zip-safe
src/stxnext.staticdeployment.egg-info/requires.txt
src/stxnext.staticdeployment.egg-info/top_level.txt
src/stxnext/staticdeployment/__init__.py
src/stxnext/staticdeployment/configure.zcml
src/stxnext/staticdeployment/interfaces.py
src/stxnext/staticdeployment/permissions.zcml
src/stxnext/staticdeployment/utils.py
src/stxnext/staticdeployment/version.txt
src/stxnext/staticdeployment/adapters/__init__.py
src/stxnext/staticdeployment/adapters/configure.zcml
src/stxnext/staticdeployment/adapters/deploymentsteps.py
src/stxnext/staticdeployment/adapters/diazo.py
src/stxnext/staticdeployment/adapters/extraconditions.py
src/stxnext/staticdeployment/adapters/transformations.py
src/stxnext/staticdeployment/app/__init__.py
src/stxnext/staticdeployment/app/configure.zcml
src/stxnext/staticdeployment/app/request.py
src/stxnext/staticdeployment/app/util.py
src/stxnext/staticdeployment/browser/__init__.py
src/stxnext/staticdeployment/browser/check_mutex.py
src/stxnext/staticdeployment/browser/configure.zcml
src/stxnext/staticdeployment/browser/preferences/__init__.py
src/stxnext/staticdeployment/browser/preferences/configure.zcml
src/stxnext/staticdeployment/browser/preferences/staticdeployment-control-panel.pt
src/stxnext/staticdeployment/browser/preferences/staticdeployment.py
src/stxnext/staticdeployment/browser/resources/asynchronous_deployment.js
src/stxnext/staticdeployment/browser/resources/deployment_spinner.gif
src/stxnext/staticdeployment/content/__init__.py
src/stxnext/staticdeployment/content/configure.zcml
src/stxnext/staticdeployment/content/store.py
src/stxnext/staticdeployment/etc/staticdeployment.ini
src/stxnext/staticdeployment/locales/stxnext.staticdeployment.pot
src/stxnext/staticdeployment/locales/pl/LC_MESSAGES/stxnext.staticdeployment.po
src/stxnext/staticdeployment/profiles/default/actionicons.xml
src/stxnext/staticdeployment/profiles/default/actions.xml
src/stxnext/staticdeployment/profiles/default/controlpanel.xml
