Metadata-Version: 1.0
Name: stxnext.staticdeployment
Version: 1.1
Summary: Deploy Plone site to static files.
Home-page: http://www.stxnext.pl/open-source
Author: STX Next Sp. z o.o, Igor Kupczyński, Radosław Jankiewicz, Wojciech Lichota, Sebastian Kalinowski
Author-email: info@stxnext.pl
License: Zope Public License, Version 2.1 (ZPL)
Keywords: plone static deploy
Platform: any
Classifier: Development Status :: 3 - Alpha
Classifier: Framework :: Zope2
Classifier: Framework :: Plone
Classifier: Intended Audience :: Developers
Classifier: License :: OSI Approved :: Zope Public License
Classifier: Natural Language :: English
Classifier: Programming Language :: Python
